{"success":true,"data":{"web":[{"url":"https://www.poolrepairs.com.au/faq/","title":"Frequently Asked Questions - Pool Repairs Perth WA","description":"How do I find out if my pool is leaking? · What resurfacing options are available for a concrete pool? · What resurfacing options are available for a fibreglass ...","position":1,"markdown":"# Frequently Asked Questions\n\nHow do I find out if my pool is leaking?\n\nA). We have written a comprehensive [downloadable PDF guide here on how to find a leak in your pool](https://www.poolrepairs.com.au/how-to-find-out-if-you-have-a-leak-in-your-swimming-pool/).\n\nWhat resurfacing options are available for a concrete pool?\n\nA). Concrete pools generally have more options available for a Renovation, these include:\n\n- Quartz Plaster\n- Fibretech Coating System\n- Pebblecrete\n- Epoxy Paint\n- Vynal Liner\n- Chlorinated rubber paint\n- Fully tiled\n\nWhat resurfacing options are available for a fibreglass pool?\n\nA). Fibreglass pools generally have fewer options available for a makeover, these include:\n\n- Fibretech Coating System\n- Epoxy Paint\n- Vynal Liner\n- Fully tiled\n\nWhat resurfacing options are available for a Vynal liner pool?\n\nA). Vynal liner pools generally have even fewer options available for a makeover these include:\n\n- Fibretech Coating System\n- Vynal Liner\n\nWhat is Fibretech Coating System?\n\nA). Fibertech Coating system has been around for at least 25 years. Fibreglass matting is laminated over the existing plaster or fiberglass surface. Using Vynal Ester Resin, which has up to 30% flexibility to laminate chop strand matting over the entire surface of the shell this system seals the entire pool.\n\nThe Laminate then gets 3 more coloured resin coats with sanding in between to produce a beautiful surface that looks exactly like a painted pool but with the structural surface strength to prevent peeling and chalking.\n\nWith a fiberglass pool this system is always the best option, rather than just “coat only” which has no structural strength. Also it does not have any seams and wont be cut, shrink or tear like a Vynal liner. A Fibretech coating can not blister like paint, or become rough and porous.\n\n**Best Features are:**\n\n- Beauty, smoothness and strength combined with flexibility,\n- Insulates against heat loss,\n- Becomes part of your pool shell (no Seams),\n- Good range of colours,\n- Strengthens a thin pool shell (in fiberglass pools),\n- Seals and repairs cracking,\n- Reduction in chemical usage,\n- Algae can’t stick to it,\n- Resists chemical abuse,\n- Eliminates and prevents black spot algae and osmosis,\n- 5 year warranty\n- Lifespan 10-15 years,\n\n**Possible negatives:**\n\n- Plaster needs to be in relatively fair condition otherwise there is a lot of\n\n\npatching prior to coating.\n- Noise and dust from sanding,\n- Can be damaged by excess chlorine,\n\nWhy consider plastering my pool then?\n\nA). Pool Plaster is by far the best option when the existing plaster surface is in bad condition or when the customer is looking for a much more natural look and feel. It is absolutely recommended that all of the existing plaster be jack-hammered off prior to the application of new plaster. This ensures that you are not having to worry about the old plaster causing any issues in the future and have a good solid base to start from. Quartz finishes such as our preferred “Rainbow Quartz” have a great colour range and can also be mix-matched to customize the look of your pool, or just have it looking like an inviting beach oasis with the “Sandy Beach “ colour.\n\n**Best Features are:**\n\n- Beautiful natural appearance and feel.\n- Back to basics system and tough strong finish for proven longevity.\n- Becomes part of your pool shell (no Seams like vinyl liner),\n- Great range of colours.\n- Faster renovation times that are less affected by weather.\n- Reduction in chemical usage and maintenance. ( as with most new surfaces).\n- 5 year warranty\n- Lifespan 10-15 plus years.\n\n**Possible negatives:**\n\n- Cannot add pool salt for 6 weeks after plastering.\n- Can be damaged or stained by poor chemical balance easier than most surfaces,\n- Does not have as much flexibility so best in traditionally built concrete pools,\n- No heat insulating properties,\n\nWhat is epoxy paint?\n\nA). Epoxy paint is a 2 pack paint which is resistant to chemicals such as salt and chlorine. It is easily applied with a brush or roller and is a good low cost alternative for pools that have a completely sound plaster surface and needs an easy makeover that can last a few years (with good care). Also it can be done DIY. (DIY kits are available)\n\n**Best Features are:**\n\n- Seals and repairs cracking,\n- Becomes part of your pool shell (no Seams),\n- Good range of colours,\n- Algae can’t stick to it\n- Resisted chemical abuse\n- Eliminates black spot algae\n- Lifespan 5-7 years.\n\n**Possible negatives:**\n\n- Plaster needs to be in very good condition because epoxy paint hasn’t enough structural strength to deal with weak areas or “pitts” in the\n\n\nplaster\n- Epoxy paint can chalk if the water balance is not kept perfect.\n- Can blister if the pool is neglected or if the surface is not in good condition.\n\nWhat is chlorinated rubber paint?\n\nA). Chlorinated rubber paint is a 1 pack pool paint that is not used as often as it once was. We do not use it because it is rated for about a 3 year lifespan which doesn’t tend to suit most backyard pool users.\n\nDo we install vinyl liners?\n\nA). No we do not, although we can replace your vinyl liner for a fiberglass one even on sand bottom floors. Its costs about 30 % more than a quality vinyl liner but is much more durable and harder to damage.\n\nWhat tiling options are available?\n\nA). When renovating your swimming pool it is a good opportunity to replace existing tiles or to incorporate more tiles into the design. These are a few options available:\n\n- Replacing existing waterline tiles with similar size ceramic tiles\n\n\n200mm x 200mm.\n- Replacing existing tile line with a similar size band 150mm – 200mm or\n\n\nup to about 300mm with ceramic or spectacular glass mosaics.\n- Tile entire step and ledge areas in 200mm x 200mm, mosaic tiles or\n\n\nnatural stone\n- Tile the entire pool surface with mosaics,\n- Tile the pool surrounds with natural sandstone, granite, Quartzite, quartz, terracotta, marble or basalt.\n\nWhy consider tiling my pool then?\n\nA). Pool tiling is a beautiful finish both to look at and to feel, that will last for many years providing the correct adhesive is used. Fully tiled pools have always been considered the premium finish. It is possible to fully tile both fibreglass and concrete pools,\n\n**Best Features are:**\n\n- Beautiful appearance and feel,\n- Good range of colours, textures and effects\n- Reduction in chemical usage,\n- Resistant to chemical damage\n- Lifespan 10-15 years.\n\n**Possible negatives:**\n\n- Expensive,\n- Time consuming process,\n- Joins and seams are visible,\n- Existing surface has to be in perfect condition\n- Grout may require periodic cleaning,\n- No heat insulating properties,\n\nHow long will it take to renovate my pool?\n\nA). With good weather each renovation process takes approximately the following conservative times.\n\n|     |     |\n| --- | --- |\n| **Work carried out** | **working days** |\n| Jack-hammering old plaster off<br>Pool header pavers<br>Waterline tiles (remove and replace)<br>Epoxy coating (7–10 days curing included)<br>Fibretech coating (1-3 days curing included)<br>Replastering (always remove old plaster)<br>Refill and balance<br>Installing new equipment<br>Skimmer box replacement<br>Water features<br>Glass Fence Install | 3-7<br>1-3<br>2-4<br>18<br>14<br>2-3<br>2-5<br>1-2<br>1-2<br>2-5<br>1-2 |\n\nThese times are as a guide only and are affected by differences in site difficulty, inclement weather, location and size of construction. We can provide written time schedules and or express service if requested at the time of quotation.\n\nWhat is the best time of the year to renovate my swimming pool?\n\nA). Every season has its positives and negatives. Although it is easier for us to work outdoors in the mild weather of spring and autumn.\n\nCan I change the shape of my swimming pool?\n\nA). Yes, we can extend or shorten your swimming pool to your requirements, we can even make it shallower, build new bench seats, a spa inside of it or a new set of steps.\n\nIs there going to be someone at my house every day during the renovation process?\n\nA). No not necessarily, some stages of the process may be filling the pool, emptying the pool, coatings curing, drying time, too windy for coating, too hot for coating, too wet for coating, ect ect, where there will not be anyone on site watching the paint dry so to speak. We will however keep you informed of what is happening with your job and our shop premises is open 7 days to handle any enquiry you may have.\n\nWhat type of lighting options is available?\n\nA). We have several types of lighting available from standard halogen lights, LED lights to fibre-optic lighting all of which can be installed retro fit to operate on a timer system for maximum effect. However mostly all the lights we install are LED which have improve greatly in recent years to become very reliable and user friendly.\n\n**Here are the benefits and possible negatives of these different lighting types**\n\n**1). Quartz halogen lights (12 volt)**\n\n**Benefits**\n\n- Least expensive\n- Powerful\n- Usually able to run off existing transformer,\n- Easy to repair,\n- Good warranty,\n\n**Possible negatives**\n\n- Globes only last about 12 months pending on brand,\n- Can only run 2 lights off 1 transformer,\n- Limited colours,\n- Limited colour change,\n\n**2). LED lights (12 volt)**\n\n**Benefits**\n\n- Great colours and effects\n- Creates a nice hue to the water\n- Usually able to run off existing transformer,\n- Long lasting 50,000 hours,\n\n**Possible negatives**\n\n- Not usually as bright as halogen lights,\n\n**3). Fibre optic lights**\n\n**Benefits**\n\n- Stunning effects with under edge lighting and water feature lights ect\n- Only one globe (light source) for all lights in the pool,\n- Good colour changing effects\n- Creates a nice hue to the water\n- Good warranty,\n\n**Possible negatives**\n\n- Very expensive,\n- Can be not bright enough,\n- Difficult installation process,\n- Performance may decrease with age\n\nShould I replace my pipe-work under the ground when I renovate my pool?\n\nA). If you are taking up old pavers or concrete around the pool then it is definitely worthwhile replacing your old pipe-work at this stage especially on 20 year old plus pools. Otherwise PVC pipe-work is very hardy if laid correctly and rarely needs replacing. Return jets are easy to replace and is recommended on most pool renovations mainly just for ascetic reasons alone. The correct method of laying new pipe-work should involve priming all joints and using preferably “green” PVC glue followed by pressure testing to ensure no leaks.\n\nShould I landscape my yard first or renovate my pool first?\n\nA). This all depends on whether you have a fiberglass or concrete pool.\n\nConcrete pools that are being re-plastered can be emptied at the beginning of a yard makeover and have the old plaster jack hammered off whilst other works are taking place. If there is machinery being used to clear a block, consideration for safety of the machine operator must be considered. The pool may need to be emptied and covered to prevent a machine operator from drowning should a machine topple into the pool.\n\n**Order of Works (Concrete Plaster)**\n\n1). Demolition and clearing of block and structures being replaced/removed.\n\n2). Jackhammer off old plaster.\n\n3). Hardscaping such as retaining wall and patios.\n\n4). Install new Skimmer box if required\n\n5). Run new pipe-work and light cables to new or existing equipment area.\n\n6). Install Bull-nose pavers and new tile line\n\n7). Paving of yard and soft-scaping with the installation of plants ect.\n\n8). Install new pool fencing or reinstate old\n\n9). Cleanout and plaster swimming pool, acid wash surface and commence filling.\n\n10). Install pool equipment and new lights, jets and fittings\n\n11). Balance water and commission pool\n\nFibreglass pools are best recoated midway in a yard makeover then headers and then paving/landscaping, due to any movement that may occur in the surrounding sand from empting and refilling. If there is machinery being used to clear a block, consideration for safety of the machine operator must be considered. The pool must be left filled and covered to prevent a machine operator from drowning should a machine topple into the pool.\n\n**Order of Works (Fibreglass Pool)**\n\n1). Demolition and clearing of block and structures being replaced/removed.\n\n2). Hardscaping such as retaining wall and patios.\n\n3). Recoating of fiberglass\n\n4). Run new pipe-work and light cables to new or existing equipment area.\n\n5). Install temporary fencing if required\n\n6). Install new Skimmer box if required and refill pool.\n\n7). Install pool equipment.\n\n8). Balance water and commission pool\n\n9). Install Bull-nose pavers\n\n10). Paving of yard and soft-scaping with the installation of plants and permanent pool fence.\n\nWhat type of preparations can I make to have the renovation process go smoother and safer around my property?\n\n- Remove any items in and around the swimming pool area that may be affected by dust from sanding or hazards that may get in the way of workers carrying products to and fro.\n- The cleaner your yard is the easier it is for us to keep leaves and sand from blowing in whilst we are coating your swimming pool.\n- Turn off reticulation around pool area and avoid watering in and\n\n\naround pool area during coating.\n- Fiberglass resin has a strong odour so it is advisable to leave windows surrounding the pool area closed. Also remove any items from the pool area that may be affected.\n- Avoid walking close to the edge of empty fiberglass and concrete\n\n\nswimming pools. This will lessen the chances of subsidence of paving and avoid dangerous falls.\n- Please keep people and pets out of the swimming pool area during renovation. This maintains a cleaner and safer working area. Do not walk in the pool this is dangerous and can also damage previous coatings unwittingly, with shoe prints, oils from feet or other contaminants.\n- During the renovation process workers need access to your pool area. Some stages may only require a few hours work per day so it is very helpful if we are able to access the pool area easily on a flexible time basis.\n\nShould I empty my pool myself and how long can it be left empty?\n\nYou should only have your pool emptied by an expert who knows how to empty your pool safely (it may also require bracing). The pool should be left empty for as little time as possible and should be refilled at the completion of the renovation in a timely manner. (It may void your warranty if left unfilled for any extra period of time).\n\nHow much will the water cost to refill my pool? Can I save the water?\n\nIt costs about $1.20 per 1,000ltrs of water and the average pool holds about 50,000ltrs of water which equates to $60.00. Also the average yearly usage of a household is about 300,000ltrs. You can save your pool water for re-use in storage tanks although it will cost far more than $50.00 and you will need lots of room in your yard to store this water so unfortunately it is not a viable option at this stage for everyone.\n\nHow often should I change the sand in my sand filter?\n\nThe typical life span of the sand in your filter according to SPASA is 3 to 5 years or every 12 months in a commercial swimming pool. What happens to the sand in the filter after time is that it becomes hard and causes an affect that is called channeling. When this occurs the water is going through holes that have been made by the water and is not actually filtering effectively through the sand. It is best to change your sand when you get your pool recoated if you believe it may require doing.\n\nCan I recoat my pool myself?\n\nYes we do provide DIY kits for epoxy paint and can guide you through this process. Fibretech and re-plastering is more difficult and requires a degree of expertise in the relative fields.\n\nCan I get someone to look after my pool regularly?\n\nBlue Star Pools offer a regular pool service to look after your pool and keep it perfectly maintained and chemically balanced all year round. This is the best way to ensure your new pool stays looking new for as long as possible.\n\nWhat heating options are available?\n\nThere is generally 4 options available for your heating options these are\n\n- Solar blanket\n- Roof Solar heating\n- Gas heater\n- Heat pump\n\n**Here are the benefits and possible negatives of these different lighting types**\n\n**1). Solar blanket**\n\n**Benefits**\n\n- Inexpensive\n- Heats pool by about 6-8 degrees\n- Stops 99.9% evaporation,\n- Required anyway with all heaters to prevent heat loss and to cut down running costs,\n- Cuts down chemical usage,\n- Helps keep out leaves and dust,\n- Good warranty,\n- $200.00 government rebate available,\n- No running cost,\n\n**Possible negatives**\n\n- They can upset the appearance of a beautiful pool,\n- May not be easy to take on or off some pools due to their shape,\n- Can be damaged by poor chemical balance,\n\n**2). Roof solar heating**\n\n**Benefits**\n\n- Heats quickly,\n- Heats pool by about 12 degrees,\n- Thermostatically controlled,\n- Coloured heat exchangers for roof to camouflage,\n- Low running cost,\n- Can get away with not having a blanket by upsizing heat exchangers,\n\n**Possible negatives**\n\n- May be visible on roof from road or back yard,\n- Can be a lot of work to run pipes for retrofit,\n- Leaks on roof may cause damage to roof or guttering,\n- Can be damaged by poor chemical balance,\n- Heating requires good warm days of sunshine,\n\n**3). Gas heating**\n\n**Benefits**\n\n- Heats very quickly,\n- Heats pool by however many degrees are required,\n- Heat all year round,\n- Thermostatically controlled,\n- Compact,\n- Auto ignition,\n- Can run off existing filtration pump with minimal pipe-work changes,\n- Can get away with not having a blanket by upsizing but will increase running cost,\n- Can be installed indoors with a flue or outdoors,\n\n**Possible negatives**\n\n- Can be expensive to run (average pool $150.00 per week constantly heated)\n- Needs a gas line run out to heater,\n- Can be damaged by poor chemical balance,\n\n**4). Heat Pump**\n\n**Benefits,**\n\n- Heat all year round,\n- Low running cost,\n- Thermostatically controlled,\n- Compact,\n- Can run off existing filtration pump with minimal pipe-work changes,\n- May get away with not having a blanket by upsizing but will increase running cost and affect performance.\n- Great warranties on most units,\n\n**Possible negatives**\n\n- Best of run with a pool blanket to reduce heat loss,\n- Needs a 15amp power supply or 3 phase power for increased efficiency,\n- Initial cost may be high,\n- Has to be outdoors in a well ventilated area,\n\nCan I convert my pool to salt?\n\nAny pool can be converted to salt without any problems apart from metal framed above ground pools which can be affected by increased corrosion. All salt water conversions require installing a “salt water chlorinator control box and electrode” commonly referred to as a “power supply and cell”. Salt is then added to the pool water and the power supply and cell uses this to produce “chlorine gas” which sanitises the water. So in effect when you convert to a salt water system you are basically producing your own chlorine at home rather than purchasing it. This will lead to cost savings, less maintenance and better water quality. The best salt water chlorinator units are “Self Cleaning” where the salt electrode (the part of the chlorinator that produces the chlorine gas) reverses polarity every 2 hours or so to prevent calcium build up on the electrode plates (cathodes and anodes). This saves even more maintenance time and results in more efficient chlorine production. In my opinion Salt water chlorinators are far more practical than liquid chemical feeders, that tend to be more complicated, require more maintenance and are more expensive to run.\n\n![](https://www.poolrepairs.com.au/wp-content/uploads/Fill-coat-in-progress-576x1024.jpg)\n\n![](data:image/svg+xml,%3Csvg%20xmlns='http://www.w3.org/2000/svg'%20viewBox='0%200%20640%20468'%3E%3C/svg%3E)\n\n![](data:image/svg+xml,%3Csvg%20xmlns='http://www.w3.org/2000/svg'%20viewBox='0%200%20765%201024'%3E%3C/svg%3E)\n\n![](data:image/svg+xml,%3Csvg%20xmlns='http://www.w3.org/2000/svg'%20viewBox='0%200%20800%20600'%3E%3C/svg%3E)\n\n[Back to top](https://www.poolrepairs.com.au/faq/# \"Back to top\") Menu\n\nNotifications","metadata":{"og:locale":"en_US","article:modified_time":"2025-02-21T13:33:45+00:00","SKYPE_TOOLBAR":"SKYPE_TOOLBAR_PARSER_COMPATIBLE","generator":["WordPress 6.7.5","Powered by WPBakery Page Builder - drag and drop page builder for WordPress.","Powered by Slider Revolution 6.7.34 - responsive, Mobile-Friendly Slider Plugin for WordPress with comfortable drag and drop interface.","WP Rocket 3.19.0.1"],"ogTitle":"Frequently Asked Questions - Pool Repairs Perth WA","og:title":"Frequently Asked Questions - Pool Repairs Perth WA","og:url":"https://www.poolrepairs.com.au/faq/","ogUrl":"https://www.poolrepairs.com.au/faq/","twitter:data1":"15 minutes","viewport":"width=device-width, initial-scale=1","google-site-verification":"CiaRUose3eEDMzzX-VYZgeTaNIf4-9jZs4LsO4IxHxs","twitter:card":"summary_large_image","twitter:label1":"Est. reading time","theme-color":"#f5f5f5","og:type":"article","modifiedTime":"2025-02-21T13:33:45+00:00","language":"en-US","robots":"index, follow, max-image-preview:large, max-snippet:-1, max-video-preview:-1","ogLocale":"en_US","ogSiteName":"Pool Repairs Perth WA","og:site_name":"Pool Repairs Perth WA","title":"Frequently Asked Questions - Pool Repairs Perth WA","scrapeId":"019d989f-b378-7321-a20f-396b7f04774e","sourceURL":"https://www.poolrepairs.com.au/faq/","url":"https://www.poolrepairs.com.au/faq/","statusCode":200,"contentType":"text/html; charset=UTF-8","timezone":"America/New_York","proxyUsed":"basic","cacheState":"miss","indexId":"9e11fd7a-a7fc-413b-8e39-07ee8d689ba5","creditsUsed":1}},{"url":"https://youngpools.com.au/faq.html","title":"Frequently Asked Questions | Young Pools Refurbishment","description":"1.What is fibreglass pool resurfacing? ; 2.What is modular liner pool refurbishment? ; 3.How do I maintain my refurbished pool? ; pool refurbishment a DIY job? ; 5.","position":2,"markdown":"Your browser does not support the video tag.\n\n\n# Frequently Asked Questions\n\n[Home](https://youngpools.com.au/index.html) FAQs\n\n## Frequently asked questions\n\n## 1.What is fibreglass pool resurfacing?\n\nFibreglass pool resurfacing is a process where a new\nlayer of fibreglass material is applied to the surface\nof a pool. This enhances its durability and gives it a\nfresh, new look.\n\n\n## 2.What is modular liner pool refurbishment?\n\nModular liner pool refurbishment involves upgrading your\nexisting liner pool by replacing the vinyl liner with a\ndurable fiberglass shell. This process not only\naddresses issues like fading, cracking, or leaks but\nalso enhances the pool’s longevity, appearance, and\noverall performance.\n\n\n## 3.How do I maintain my refurbished pool?\n\nMaintaining your refurbished pool involves regular\ncleaning, balancing water chemistry, and inspecting the\npool equipment. If properly maintained, your pool's\nrefurbished surface can last for many years.\n\n\n## 4.Is pool refurbishment a DIY job?\n\nPool refurbishment is a complex process that requires\nspecialized equipment and skills. To ensure the\nlongevity of your pool and safety of the users, it's\nbest to entrust this task to professionals.\n\n\n## 5.How often should a concrete pool be  refurbished?\n\nWhen resurfaced with fiberglass, a concrete pool can\nlast another 20–25 years before requiring refurbishment\nagain. However, the exact timing can vary depending on\nthe pool’s condition, usage, and how well it's\nmaintained.\n\n\n## 6.Can I refurbish my pool myself?\n\nWhile it's possible, pool refurbishment requires\nspecialized skills and equipment. It's recommended to\nhire professionals.\n\n\n## 7.Can I change the shape of my pool during  refurbishment?\n\nYes, modifications to the shape of your pool can be made\nduring refurbishment, depending on the pool type.\n\n\n## 8.Is it worth investing in pool  refurbishment?\n\nYes. Refurbishing your pool not only enhances its\naesthetics but also increases property value and ensures\nsafety.\n\n\n## 9.Is there a best time of year to refurbish a  pool?\n\nWhile some prefer refurbishing during the cooler months\nto have their pool ready for summer, we’re fully\nequipped to carry out refurbishments year-round. Our\nstreamlined processes ensure minimal downtime, no matter\nthe season.\n\n\n## 10.What should I expect during the  refurbishment process?\n\nExpect draining, surface preparation, repairs,\nresurfacing or liner installation, and system upgrades\nif needed.\n\n\n## 11.Will the refurbishment process be noisy or  disruptive?\n\nThere may be some noise and activity, especially during\nthe initial stages, but we aim to minimize disruptions.\n\n\n## 12.What warranties or guarantees do you  offer?\n\nWe offer industry-standard warranties on materials and\nworkmanship. Details will be provided during the\nconsultation.\n\n\n## 13.How do I get a quote for pool  refurbishment?\n\nYou can contact us via phone or our website to schedule\na free on-site consultation and get a customized quote.\n\n\n## 14.What areas do you service?\n\nWe service a wide area, including metropolitan and\nregional zones. Please contact us to check your\nlocation.\n\n\n[Young Pools Refurbishment Schedule a Site Visit Today!](https://youngpools.com.au/contact.html)","metadata":{"google-site-verification":"99CcR-2SPLldly3zY9D475VmspJ3H0AZaV171sRpUOs","title":"Frequently Asked Questions | Young Pools Refurbishment","viewport":"width=device-width, initial-scale=1.0, user-scalable=0","language":"en","favicon":"https://youngpools.com.au/assets/img/favicon.png","scrapeId":"019d989f-b378-7321-a20f-3ccfc7acf658","sourceURL":"https://youngpools.com.au/faq.html","url":"https://youngpools.com.au/faq.html","statusCode":200,"contentType":"text/html","timezone":"America/New_York","proxyUsed":"basic","cacheState":"miss","indexId":"df82e2cb-d09b-4661-8df0-29383171757c","creditsUsed":1}},{"url":"https://localpoolrenovations.com.au/information/109-concrete-pool-renovation-faq-repairs-tiling-restoration-in-melbourne","title":"Frequently asked questions - Local Pool Renovations","description":"This page contains up to date and useful information regarding pool maintenance, repair and renovation. 0407 666 999.","position":3,"markdown":"When you have any questions, you can rely on us to find the answer. Here you will find a list of common questions and answers. If you have any questions feel free to email us.\n\n# Frequently Asked Questions About Swimming Pool Renovations\n\n## Swimming Pool FAQs\n\nEverything to know about swimming pool renovation services, explained through the most common FAQs.\n\n### Swimming Pool Questions\n\n#### FAQ Quick Links\n\nClick on the topic to explore our most common questions and answers.\n\n#### Q&A\n\n[Pool Renovation Questions](https://localpoolrenovations.com.au/information/109-concrete-pool-renovation-faq-repairs-tiling-restoration-in-melbourne#pool-renovation-questions)\n\n[General Pool Tiling Questions](https://localpoolrenovations.com.au/information/109-concrete-pool-renovation-faq-repairs-tiling-restoration-in-melbourne#pool-tiling-questions)\n\n[Swimming Pool Painting Questions](https://localpoolrenovations.com.au/information/109-concrete-pool-renovation-faq-repairs-tiling-restoration-in-melbourne#swimming-pool-painting-questions)\n\n[Pool Resurfacing Questions](https://localpoolrenovations.com.au/information/109-concrete-pool-renovation-faq-repairs-tiling-restoration-in-melbourne#pool-resurfacing-questions)\n\n[Pool Coping Questions](https://localpoolrenovations.com.au/information/109-concrete-pool-renovation-faq-repairs-tiling-restoration-in-melbourne#pool-coping-questions)\n\n[Swimming Pool Light Questions](https://localpoolrenovations.com.au/information/109-concrete-pool-renovation-faq-repairs-tiling-restoration-in-melbourne#swimming-pool-light-questions)\n\n### Pool Renovation Questions\n\nResurfacing vs repainting — which lasts longer?![5oVpqEAAAAGSURBVAMAybVjtYtpiX4AAAAASUVORK5CYII= Frequently asked questions](<Base64-Image-Removed>)\n\nResurfacing with pebble or full tiling typically outlasts paint. Paint is lower cost upfront but often needs recoating within a few years, especially under strong UV and chemical exposure.\n\nFor more information about pool resurfacing visit: [Pool Resurfacing Melbourne](https://localpoolrenovations.com.au/options/72-swimming-pool-resurfacing)\n\nWhat does a pool renovation include?![5oVpqEAAAAGSURBVAMAybVjtYtpiX4AAAAASUVORK5CYII= Frequently asked questions](<Base64-Image-Removed>)\n\nTypical scope includes new tiling, resurfacing, coping and paving, rust repairs, painting, and design updates. The mix depends on pool condition, budget, and style goals.\n\nFor a breakdown of services visit [Swimming Pool Renovation Options](https://localpoolrenovations.com.au/pool-resurfacing-options-ideas).\n\n\nHow long does a pool renovation take?![5oVpqEAAAAGSURBVAMAybVjtYtpiX4AAAAASUVORK5CYII= Frequently asked questions](<Base64-Image-Removed>)\n\nTimeframes usually range from two to eight weeks. Minor repairs finish faster; full retile plus paving and design changes take longer due to curing times and sequencing of trades.\n\nLearn more at [Pool Renovations Melbourne.](https://localpoolrenovations.com.au/)\n\nPool renovation cost Melbourne — how much?![5oVpqEAAAAGSURBVAMAybVjtYtpiX4AAAAASUVORK5CYII= Frequently asked questions](<Base64-Image-Removed>)\n\nEntry-level projects in Melbourne start around the low-twenties 20,000 (AUD). Premium outcomes with full tiling, new coping, and paving can exceed 50,000 depending on materials, size, and site access.\n\nFor more technical tiling information visit:  [Pool tiling FAQ](https://localpoolrenovations.com.au/information/98-tiled-pool-information)\n\nIs a swimming pool drained for renovations?![5oVpqEAAAAGSURBVAMAybVjtYtpiX4AAAAASUVORK5CYII= Frequently asked questions](<Base64-Image-Removed>)\n\nYes, most pool renovations require draining. Some repairs may not require draining the pool.\n\nMore information can be found at [Hydrostatic Valve Removal Guide.](https://localpoolrenovations.com.au/information/66-hydrovalve)\n\nWhat are the signs that a swimming pool needs renovation?![5oVpqEAAAAGSURBVAMAybVjtYtpiX4AAAAASUVORK5CYII= Frequently asked questions](<Base64-Image-Removed>)\n\nLeaks, cracks, rust spots, loose tiles, stained surfaces, or outdated design indicate renovation value. High maintenance time or chemical use also signals deterioration since the water balance changes frequently when inside an unstable pool surface.\n\nMore insights at [Swimming Pool Repairs Melbourne.](https://localpoolrenovations.com.au/options/2-service-repairs-and-resurfacing-swimming-pools)\n\n### General Pool Tiling Questions\n\nAre waterline tiles necessary?![5oVpqEAAAAGSURBVAMAybVjtYtpiX4AAAAASUVORK5CYII= Frequently asked questions](<Base64-Image-Removed>)\n\nWaterline tiles are recommended to reduce staining from fluctuating water chemistry and to create a clean edge that is easier to maintain. While they also create a great look for swimming pools and can be considered one of the most recognisable pool features, waterline tiles were soley installed as a solution to the pools staining problem on the water level/edge.\n\nMore insights at [Swimming Pool Repairs Melbourne.](https://localpoolrenovations.com.au/options/2-service-repairs-and-resurfacing-swimming-pools)\n\nWhy do pool tiles fall off?![5oVpqEAAAAGSURBVAMAybVjtYtpiX4AAAAASUVORK5CYII= Frequently asked questions](<Base64-Image-Removed>)\n\nCommon causes include substrate movement, inadequate surface preparation, unsuitable adhesives, poor expansion joints, or water chemistry issues degrading grout and glue lines.\n\nFor expert tiling visit [Best Swimming Pool Tiler Melbourne.](https://localpoolrenovations.com.au/options/70-swimming-pool-tiler-melbourne)\n\nBest tiles for swimming pools?![5oVpqEAAAAGSURBVAMAybVjtYtpiX4AAAAASUVORK5CYII= Frequently asked questions](<Base64-Image-Removed>)\n\nFully tiled or waterline tile finishes with ceramic / porcelain mosaics offer durability, chemical resistance, and a luxury look. Slip-resistant options and UV-stable grout also helps improve longevity.\n\nExplore more at [Swimming Pool Tiling Melbourne.](https://localpoolrenovations.com.au/options/70-swimming-pool-tiler-melbourne)\n\nHow long do pool tiles last?![5oVpqEAAAAGSURBVAMAybVjtYtpiX4AAAAASUVORK5CYII= Frequently asked questions](<Base64-Image-Removed>)\n\nHigh-quality ceramic / porcelain pool tiles can last 30+ years when installed correctly. Lifespan depends on installation quality, choice of materials used for installation and pool water chemistry.\n\nFully tiled pools are reknown for lasting over 30 years, with many still being used frequently that have been tiled even after 40 & 50 years of age. More often than not, owners of a fully tiled pool retile their pool because they don't like the tile colours and want to update.\n\nLearn more at [Swimming Pool Tiling Melbourne.](https://localpoolrenovations.com.au/options/70-swimming-pool-tiler-melbourne)\n\nCan old pool tiles be replaced without retiling the whole pool?![5oVpqEAAAAGSURBVAMAybVjtYtpiX4AAAAASUVORK5CYII= Frequently asked questions](<Base64-Image-Removed>)\n\nYes, damaged or missing tiles can be replaced individually, though colour matching may be difficult on older pools. Larger damaged sections often indicate the need for full retiling. This is one of the great things about tiled pools, if any damage occurs they can be repaired in sections.\n\nFor repair options visit [Pool Tile Replacement Melbourne.](https://localpoolrenovations.com.au/pool-repairs-melbourne)\n\nAre glass pool tiles reliable?![5oVpqEAAAAGSURBVAMAybVjtYtpiX4AAAAASUVORK5CYII= Frequently asked questions](<Base64-Image-Removed>)\n\nGlass tiles are often marketed as premium, but in practice they are prone to failure. Even with correct installation, changes in temperature, getting wet and then drying (when out of the water) and pool movement commonly cause glass tiles to loosen or fall off. For more durable results, ceramic pool tiles are recommended.\n\nDisclaimer:\n\nThis answer reflects our professional opinion. While others may hold different views, our perspective comes from years of repairing and renovating pools, where we see the long-term effects of different material choices. We share this openly and note that we have no financial interest in whether glass tiles are used or not.\n\n\nLearn more at [Swimming Pool Tiling Melbourne.](https://localpoolrenovations.com.au/options/96-new-swimming-pool-tiling)\n\nDo glass pool tiles fall off?![5oVpqEAAAAGSURBVAMAybVjtYtpiX4AAAAASUVORK5CYII= Frequently asked questions](<Base64-Image-Removed>)\n\nYes, glass tiles frequently detach over time. Expansion and contraction from temperature changes make them more vulnerable than ceramic mosaics. This issue is widely observed even in high-end installations, temperature changes and tiles outside of the water above the waterline or on the spillway between the spa and the pool tend to be the most affected, this is because those glass tiles are exposed to water and air, wet / dry & hot / cold changes severely affect glass tile installations.\n\n# Glass tiles frequently falling off.\n\nDisclaimer: This answer reflects our professional opinion. While others may hold different views, our perspective comes from years of repairing and renovating pools, where we see the long-term effects of different material choices. We share this openly and note that we have no financial interest in whether glass tiles are used or not.\n\n\nFor expert advice visit Best [Swimming Pool Tiler Melbourne.](https://localpoolrenovations.com.au/options/70-swimming-pool-tiler-melbourne)\n\n### Swimming Pool Painting Questions\n\nWhich is the best pool paint? ![5oVpqEAAAAGSURBVAMAybVjtYtpiX4AAAAASUVORK5CYII= Frequently asked questions](<Base64-Image-Removed>)\n\nEpoxy pool paint is the most durable and long-lasting. Chlorinated rubber and acrylic pool paints are also options but generally don’t last as long as epoxy.\n\nFor paint information visit: [Pool paint Melbourne.](https://localpoolrenovations.com.au/options/62-pool-painting-experts)\n\nHow long does pool paint last?![5oVpqEAAAAGSURBVAMAybVjtYtpiX4AAAAASUVORK5CYII= Frequently asked questions](<Base64-Image-Removed>)\n\nEpoxy pool paint can last up to 7–10 years with proper preparation and maintenance, while acrylic or rubber-based paints usually last 2–5 years before requiring a recoat.\n\nFor expert information visit: [Best swimming pool painter Melbourne.](https://localpoolrenovations.com.au/options/62-pool-painting-experts)\n\nIs it possible to paint over old pool paint?![5oVpqEAAAAGSURBVAMAybVjtYtpiX4AAAAASUVORK5CYII= Frequently asked questions](<Base64-Image-Removed>)\n\nYes, but only if the old coating is compatible and in decent condition. If the type of existing paint is unknown, a small patch test should be done, or the existing surface should be stripped to avoid peeling and adhesion issues.\n\nExplore more at [Swimming pool painting Melbourne.](https://localpoolrenovations.com.au/options/62-pool-painting-experts)\n\nHow long after painting a pool can you fill it with water?![5oVpqEAAAAGSURBVAMAybVjtYtpiX4AAAAASUVORK5CYII= Frequently asked questions](<Base64-Image-Removed>)\n\nMost pool paints require a curing period. Epoxy paint usually needs 5–7 days to cure, while acrylic-based paints may only need 2–3 days, depending on weather conditions.\n\nLearn more at [Epoxy pool painting](https://localpoolrenovations.com.au/)\n\nIs pool paint waterproof?![5oVpqEAAAAGSURBVAMAybVjtYtpiX4AAAAASUVORK5CYII= Frequently asked questions](<Base64-Image-Removed>)\n\nYes, when fully cured, pool paint provides a waterproof coating that protects the underlying pool shell from water penetration, chemical exposure, and UV damage.\n\nFor repair options visit [Pool painting business Melbourne.](https://localpoolrenovations.com.au/options/62-pool-painting-experts)\n\nDo pools need to be acid washed before painting?![5oVpqEAAAAGSURBVAMAybVjtYtpiX4AAAAASUVORK5CYII= Frequently asked questions](<Base64-Image-Removed>)\n\nYes, acid washing is strongly recommended to remove algae, minerals, and chalky residue. It ensures the paint bonds properly to the original pool surface.\n\nLearn more at [Swimming Pool Cleaning Melbourne.](https://localpoolrenovations.com.au/options/69-expert-pool-cleaning-service)\n\nWhy does pool paint peel?![5oVpqEAAAAGSURBVAMAybVjtYtpiX4AAAAASUVORK5CYII= Frequently asked questions](<Base64-Image-Removed>)\n\nWater chemistry imbalances breaking down the paint film is the most common cause of flaking and peeling, second to this is UV exposure, sometimes filling the pool too soon after painting or painting over an incompatible coating.\n\nFor expert advice visit [Pool paint experts](https://localpoolrenovations.com.au/options/62-pool-painting-experts)\n\n### Pool Resurfacing Questions\n\nWhat is pool resurfacing? and why is it needed.![5oVpqEAAAAGSURBVAMAybVjtYtpiX4AAAAASUVORK5CYII= Frequently asked questions](<Base64-Image-Removed>)\n\nPool resurfacing is the process of applying a new interior finish to restore the look and integrity of an old pool. It’s needed when the surface becomes rough, stained, cracked, or starts leaking.\n\nFor resurfacing information visit: [Pool Resurfacing Melbourne.](https://localpoolrenovations.com.au/options/72-swimming-pool-resurfacing)\n\nHow long does a pool render or pebble interior last?![5oVpqEAAAAGSURBVAMAybVjtYtpiX4AAAAASUVORK5CYII= Frequently asked questions](<Base64-Image-Removed>)\n\nA properly installed pebble surface can last 15–25 years depending on the material, water chemistry maintenance, and exposure to weather conditions.\n\nFor expert resurfacing visit: [Swimming pool resurfacing Melbourne.](https://localpoolrenovations.com.au/options/72-swimming-pool-resurfacing)\n\nWhat is the difference between pebble, marblesheen, and quartzon?![5oVpqEAAAAGSURBVAMAybVjtYtpiX4AAAAASUVORK5CYII= Frequently asked questions](<Base64-Image-Removed>)\n\nPebble finishes use tiny exposed stones mixed into cement for a non-slip, durable surface. Marblesheen is a plaster made from crushed marble and white cement. Quartzon is a marble-based interior that includes quartz for added sparkle. Pebble is the strongest option, Marblesheen is a close second, Quartzon is the weakest and the most known for having problems.\n\nExplore more at [Pebble interior installer Melbourne](https://localpoolrenovations.com.au/options/72-swimming-pool-resurfacing)\n\nIs it possible to change a pool surface from marblesheen to pebble?![5oVpqEAAAAGSURBVAMAybVjtYtpiX4AAAAASUVORK5CYII= Frequently asked questions](<Base64-Image-Removed>)\n\nYes, old surfaces can usually be resurfaced with pebble, the pool needs to be properly prepared by a professional. Many pool owners resurface from Quartzon or Marblesheen to Pebble interiors for durability and modern aesthetics.\n\nLearn more at: [How to update a swimming pool interior.](https://localpoolrenovations.com.au/options/72-swimming-pool-resurfacing)\n\nIs pebble interiors waterproof?![5oVpqEAAAAGSURBVAMAybVjtYtpiX4AAAAASUVORK5CYII= Frequently asked questions](<Base64-Image-Removed>)\n\nNo, when fully cured a pebble interior will provide a watertight / waterproof type of surface that will help retain the pool water but won't completely stop water from leaking. Resurfacing does protect the underlying concrete pool shell from water penetration, chemical exposure, and UV damage.\n\nFor repair options visit [Pool interior coating Melbourne.](https://localpoolrenovations.com.au/options/72-swimming-pool-resurfacing)\n\nWhy does a pool surface become rough or sharp?![5oVpqEAAAAGSURBVAMAybVjtYtpiX4AAAAASUVORK5CYII= Frequently asked questions](<Base64-Image-Removed>)\n\nThis often happens as rendered pool interiors age, the surface dissolves, it becomes etched from unbalanced water chemistry or installed close to the surface of the water be affected by UV. Resurfacing is usually the only long-term fix.\n\nLearn more at [Swimming pool rendering Melbourne.](https://localpoolrenovations.com.au/options/72-swimming-pool-resurfacing)\n\nHow to know when it’s time to resurface a pool?![5oVpqEAAAAGSURBVAMAybVjtYtpiX4AAAAASUVORK5CYII= Frequently asked questions](<Base64-Image-Removed>)\n\nSigns include staining that won’t clean off, surface roughness, cracks, water loss, algae growth, pits / holes, circular bulges, calcium spots throughout the pool surface, lineal calcium build-ups & constantly changing water parameters. It can be one of the listed problems or any combination of them.\n\nThese are all indicators that the pool’s interior finish has worn beyond repair.\n\nFor expert advice: visit [Pool renovation experts](https://localpoolrenovations.com.au/options/72-swimming-pool-resurfacing)\n\n### Pool Coping Questions\n\nWhat is pool coping?![5oVpqEAAAAGSURBVAMAybVjtYtpiX4AAAAASUVORK5CYII= Frequently asked questions](<Base64-Image-Removed>)\n\nPool coping is the edging that sits on top of a swimming pool shell, forming the border between the pool structure and the surrounding paving. It protects the shell from water damage, provides a safe edge for swimmers, and creates a finished, polished look around the pool. Simply, it is the edge of a swimming pool that people sit on when sitting with just their legs in the water.\n\nFor coping information visit: [Pool coping Melbourne.](https://localpoolrenovations.com.au/options/74-swimming-pool-coping)\n\nIs pool coping necessary?![5oVpqEAAAAGSURBVAMAybVjtYtpiX4AAAAASUVORK5CYII= Frequently asked questions](<Base64-Image-Removed>)\n\nYes, pool coping is essential because it protects the pool structure, covers the concrete shell, and provides a safe edge to enter and exit the pool. Without coping, the pool surface is exposed to water damage and faster deterioration.\n\nFor more info see [Pool Coping Melbourne.](https://localpoolrenovations.com.au/options/74-swimming-pool-coping)\n\nHow often should pool coping be replaced?![5oVpqEAAAAGSURBVAMAybVjtYtpiX4AAAAASUVORK5CYII= Frequently asked questions](<Base64-Image-Removed>)\n\nPool coping generally lasts 10 to 20 years, depending on the material and how well the pool is maintained. If you notice cracks, loose edges, or erosion, it’s time to consider replacing it.\n\n### Swimming pool coping replacement\n\nCoping used to commonly be installed using mortar, when the pool ages the mortar becomes unstuck from the pool shell, when this happens usually the top row of swimming pool tiles fall off. These are signs the coping needs replacement and likely the waterline tiles too.\n\nFor more info view [Pool Coping & Paving Melbourne.](https://localpoolrenovations.com.au/options/74-swimming-pool-coping)\n\nCan new coping be installed over old coping?![5oVpqEAAAAGSURBVAMAybVjtYtpiX4AAAAASUVORK5CYII= Frequently asked questions](<Base64-Image-Removed>)\n\nNo. Old coping needs to be removed before new coping is installed to ensure the bond and waterproofing are correct. Installing over old coping can lead to future failures. The only exception is if the coping is rendered pebblecrete.\n\nFor more info see [Pool Coping Replacement Melbourne.](https://localpoolrenovations.com.au/options/74-swimming-pool-coping)\n\nWhat is the difference between pool coping and pool paving?![5oVpqEAAAAGSURBVAMAybVjtYtpiX4AAAAASUVORK5CYII= Frequently asked questions](<Base64-Image-Removed>)\n\nCoping is the stone or tile that sits on the pool edge and covers the shell, while paving refers to the surrounding area around the pool. Coping provides structure and protection, while paving provides the usable entertainment area. There should almost always be an expansion joint between the coping and paving.\n\nFor more info see [Pool Coping and Paving Melbourne.](https://localpoolrenovations.com.au/options/74-swimming-pool-coping)\n\nIs professional installation of pool coping important?![5oVpqEAAAAGSURBVAMAybVjtYtpiX4AAAAASUVORK5CYII= Frequently asked questions](<Base64-Image-Removed>)\n\nAbsolutely. Poorly installed coping can lead to water leaks, shifting stones, and safety hazards. Using an experienced pool renovator ensures the coping is secure, watertight, and built to last.​\n\nFor more info view [Pool Tiling Melbourne.](https://localpoolrenovations.com.au/information/98-tiled-pool-information)\n\nHow much does pool coping cost?![5oVpqEAAAAGSURBVAMAybVjtYtpiX4AAAAASUVORK5CYII= Frequently asked questions](<Base64-Image-Removed>)\n\nThe average mid-range cost of pool coping is $10,000 per pool, including stone supply. Cost depends on the material chosen and the scope of installation. On average in Melbourne, prices start from around $150 per linear meter for basic concrete or reconstituted stone coping and can exceed $400 per linear meter for premium options like bluestone or travertine.\n\nInstallation factors such as pool shape, preparation, and custom cutting also influence the final cost, example: bullnose stone is an added cost of $25 per metre for the process of creating a bullnosed edge.\n\nSquare / rectangle pools are cheaper than freeform / kidney-shaped swimming pools. Most installers have a minimum price based on size, so pool owners that have a tiny pool will be charged at the minimum rate of 26 Lineal metres.\n\nFor more info see [Pool Coping Costs Melbourne.](https://localpoolrenovations.com.au/information/98-tiled-pool-information)\n\n### Swimming Pool Light Questions\n\nAre LED pool lights worth it?![5oVpqEAAAAGSURBVAMAybVjtYtpiX4AAAAASUVORK5CYII= Frequently asked questions](<Base64-Image-Removed>)\n\nYes, LED lights use up to 80% less electricity than halogen, last 5–7 times longer, and offer multiple colours and smart-control options. While the upfront cost is higher, the long-term savings make them the best investment.\n\nFor LED information visit: [Pool Lights Melbourne.](https://localpoolrenovations.com.au/options/73-led-pool-lights)\n\nCan pool lights be changed without draining the pool?![5oVpqEAAAAGSURBVAMAybVjtYtpiX4AAAAASUVORK5CYII= Frequently asked questions](<Base64-Image-Removed>)\n\nYes, most pool lights are designed for replacement without the need to drain a swimming pool.\n\nFor more info see [Swimming pool lighting guide](https://localpoolrenovations.com.au/options/73-led-pool-lights)\n\nHow many lights are needed for a swimming pool?![5oVpqEAAAAGSURBVAMAybVjtYtpiX4AAAAASUVORK5CYII= Frequently asked questions](<Base64-Image-Removed>)\n\nThis depends on pool size, shape, and depth. A standard residential pool often requires 2 LED lights for even coverage, while larger pools may need 4 or more.\n\nFor more info see [Swimming pool lighting guide](https://localpoolrenovations.com.au/options/73-led-pool-lights)\n\nIs a transformer needed for pool lights?![5oVpqEAAAAGSURBVAMAybVjtYtpiX4AAAAASUVORK5CYII= Frequently asked questions](<Base64-Image-Removed>)\n\nYes, most pool lights require a transformer to step down standard household voltage (240V in Australia) to a safe low voltage, usually 12V or 24V. This ensures the lights operate safely under water.\n\nFor more info see [Pool light Replacement Melbourne.](https://localpoolrenovations.com.au/options/73-led-pool-lights)\n\nHow much does it cost to install pool lights?![5oVpqEAAAAGSURBVAMAybVjtYtpiX4AAAAASUVORK5CYII= Frequently asked questions](<Base64-Image-Removed>)\n\nThe cost varies depending on the type of light and installation requirements. On average, professional installation in Melbourne ranges from $800–$1,500 per light including labour and fittings.\n\nFor more info see [Pool light installers Melbourne.](https://localpoolrenovations.com.au/options/73-led-pool-lights)\n\nWho can install pool lights?![5oVpqEAAAAGSURBVAMAybVjtYtpiX4AAAAASUVORK5CYII= Frequently asked questions](<Base64-Image-Removed>)\n\nIf pool lights are hardwired they must be replaced by a licenced electrician. If the pool lights are 12v or less then anyone can replace or install pool lights, if someone is unsure - then it is best if an electrician is called in.\n\nIf you need more options, view [Pool Electrician Melbourne](https://localpoolrenovations.com.au/information/97-swimming-pool-electrical-services)\n\n↑ Top","metadata":{"ogUrl":"https://localpoolrenovations.com.au/information/109-concrete-pool-renovation-faq-repairs-tiling-restoration-in-melbourne","ogSiteName":"Local Pool Renovations","robots":"index,follow,snippet","theme-color":"#1a73e3","twitter:card":"summary_large_image","twitter:description":"Frequently Asked Questions About Swimming Pool Renovations","og:description":"This page contains up to date and useful information regarding pool maintenance, repair and renovation. 0407 666 999","og:site_name":"Local Pool Renovations","twitter:title":"Concrete Pool Renovation FAQ – Repairs, Tiling & Restoration in Melbou","ogTitle":"Frequently asked questions","rights":"Copyright Local Pool Renovations.","og:title":"Frequently asked questions","og:url":"https://localpoolrenovations.com.au/information/109-concrete-pool-renovation-faq-repairs-tiling-restoration-in-melbourne","description":"This page contains up to date and useful information regarding pool maintenance, repair and renovation. 0407 666 999","title":"Frequently asked questions","og:type":"article","ogDescription":"This page contains up to date and useful information regarding pool maintenance, repair and renovation. 0407 666 999","viewport":"width=device-width, initial-scale=1.0","language":"en-AU","keywords":"FAQ, swimming pool, ?, answer, question, pool information,","favicon":"https://localpoolrenovations.com.au/templates/localpoolrenovs2025/images/favicon3.png","scrapeId":"019d989f-b378-7321-a20f-424e1e2ea49c","sourceURL":"https://localpoolrenovations.com.au/information/109-concrete-pool-renovation-faq-repairs-tiling-restoration-in-melbourne","url":"https://localpoolrenovations.com.au/information/109-concrete-pool-renovation-faq-repairs-tiling-restoration-in-melbourne","statusCode":200,"contentType":"text/html; charset=utf-8","timezone":"America/New_York","proxyUsed":"basic","cacheState":"miss","indexId":"1ecc79c9-75df-41d9-9694-0ff2182b462b","creditsUsed":1}},{"url":"https://ecopoly.au/blog/a-complete-pool-resurfacing-guide-benefits-costs-and-maintenance-tips","title":"A Complete Pool Resurfacing Guide: Benefits, Costs, and ...","description":"Learn everything about pool resurfacing, including steps, benefits, costs, and maintenance tips to keep your pool safe, beautiful, ...","position":4,"markdown":"[![EcoPoly](https://content.app-sources.com/s/752384649097675301/uploads/Images/Logo_white-5248060.webp?format=webp)](https://ecopoly.au/)\n\n[1800 717 548](tel:1800717548)\n\n[![EcoPoly](https://content.app-sources.com/s/752384649097675301/uploads/Images/Logo_white-5248060.webp?format=webp)](https://ecopoly.au/)\n\n[1800 717 548](tel:1800717548)\n\n- [Cart](https://ecopoly.au/store/cart \"Cart\")\n\n![](https://content.app-sources.com/s/752384649097675301/uploads/Blogs/Blogs_banner-8931531.jpg?format=webp)\n\n![A Complete Pool Resurfacing Guide: Benefits, Costs, and Maintenance Tips](https://content.app-sources.com/s/752384649097675301/uploads/About_Us/A-Complete-Pool-Resurfacing-Guide-Benefits-Costs-and-Maintenance-Tips-1732184.png?format=webp)\n\nYour cart is empty [Continue](https://ecopoly.au/store)\n\nShopping Cart\n\nSubtotal:\n\nDiscount\n\nDiscount\n\n[View Cart](https://ecopoly.au/store/cart) [Checkout](https://ecopoly.au/store/checkout)\n\nVisitor Information ReportingAllow this website to collect visitor and device info for statistical purposes.\n\nSave Changes\n\nView Details\n\nQuantity\n\n-+\n\nSold Out\n\nMay I help you?\n\n![](https://cdn.botpenguin.com/assets/avatars/profile-27.svg)\n\n<  \\>\n\nreCAPTCHA\n\nRecaptcha requires verification.\n\nprotected by **reCAPTCHA**","metadata":{"ogImage":"https://content.app-sources.com/s/752384649097675301/uploads/About_Us/A-Complete-Pool-Resurfacing-Guide-Benefits-Costs-and-Maintenance-Tips-1732184.png","twitter:image":"https://content.app-sources.com/s/752384649097675301/uploads/About_Us/A-Complete-Pool-Resurfacing-Guide-Benefits-Costs-and-Maintenance-Tips-1732184.png","twitter:description":"Learn everything about pool resurfacing, including steps, benefits, costs, and maintenance tips to keep your pool safe, beautiful, and long-lasting.","ogDescription":"Learn everything about pool resurfacing, including steps, benefits, costs, and maintenance tips to keep your pool safe, beautiful, and long-lasting.","description":"Learn everything about pool resurfacing, including steps, benefits, costs, and maintenance tips to keep your pool safe, beautiful, and long-lasting., Learn everything about pool resurfacing, including steps, benefits, costs, and maintenance tips to keep your pool safe, beautiful, and long-lasting.","twitter:card":"summary","ogUrl":"http://ecopoly.au/blog/a-complete-pool-resurfacing-guide-benefits-costs-and-maintenance-tips","og:url":"http://ecopoly.au/blog/a-complete-pool-resurfacing-guide-benefits-costs-and-maintenance-tips","twitter:url":"http://ecopoly.au/blog/a-complete-pool-resurfacing-guide-benefits-costs-and-maintenance-tips","og:type":"website","twitter:title":"A Complete Pool Resurfacing Guide: Benefits, Costs, and Maintenance Tips","title":"A Complete Pool Resurfacing Guide: Benefits, Costs, and Maintenance Tips","ogSiteName":"EcoPoly","ogTitle":"A Complete Pool Resurfacing Guide: Benefits, Costs, and Maintenance Tips","og:site_name":"EcoPoly","og:title":"A Complete Pool Resurfacing Guide: Benefits, Costs, and Maintenance Tips","viewport":["width=device-width, initial-scale=1.0, minimum-scale=1.0","width=device-width, initial-scale=1"],"og:description":"Learn everything about pool resurfacing, including steps, benefits, costs, and maintenance tips to keep your pool safe, beautiful, and long-lasting.","image":["https://content.app-sources.com/s/752384649097675301/uploads/About_Us/A-Complete-Pool-Resurfacing-Guide-Benefits-Costs-and-Maintenance-Tips-1732184.png","https://content.app-sources.com/s/752384649097675301/uploads/About_Us/A-Complete-Pool-Resurfacing-Guide-Benefits-Costs-and-Maintenance-Tips-1732184.png"],"url":"https://ecopoly.au/blog/a-complete-pool-resurfacing-guide-benefits-costs-and-maintenance-tips","name":"A Complete Pool Resurfacing Guide: Benefits, Costs, and Maintenance Tips","language":"en","og:image":"https://content.app-sources.com/s/752384649097675301/uploads/About_Us/A-Complete-Pool-Resurfacing-Guide-Benefits-Costs-and-Maintenance-Tips-1732184.png","favicon":"https://content.app-sources.com/s/752384649097675301/uploads/About_Us/favicon-5662593.webp","scrapeId":"019d989f-b379-75aa-adf2-604959c84091","sourceURL":"https://ecopoly.au/blog/a-complete-pool-resurfacing-guide-benefits-costs-and-maintenance-tips","statusCode":200,"contentType":"text/html;charset=UTF-8","timezone":"America/New_York","proxyUsed":"basic","cacheState":"miss","indexId":"ba339012-7b1e-4b1d-a953-dc302642c2dd","creditsUsed":1}},{"url":"https://pooltekresurfacing.com.au/how-to-tell-when-your-pool-needs-resurfacing/","title":"How To Tell When Your Pool Needs Resurfacing","description":"Visible Cracks: Surface cracks are a common indication that your pool needs resurfacing. · Chipping or Peeling · Stains and Discoloration · Rough Texture · Leaking ...","position":5,"markdown":"## How To Tell When Your Pool Needs Resurfacing\n\n[BY Admin](https://pooltekresurfacing.com.au/author/pooltekr/) [March 10, 2026](https://pooltekresurfacing.com.au/2026/03/10/)\n\nKnowing when your pool needs resurfacing is key to maintaining its appearance, functionality, and safety. Here are some signs to look out for:\n\n1. **Visible Cracks**: Surface cracks are a common indication that your pool needs resurfacing. Small cracks may not be a big issue, but larger or expanding cracks can lead to more significant problems.\n2. **Chipping or Peeling**: If you notice that the plaster or finish of your pool is chipping, peeling, or flaking, it’s a sign that the surface is wearing out and may need to be replaced.\n3. **Stains and Discoloration**: Persistent stains or discoloration that won’t come out with cleaning can indicate that the pool’s surface is degrading and needs resurfacing.\n4. **Rough Texture**: Over time, the pool’s surface can become rough or abrasive. This rough texture can be uncomfortable for swimmers and may indicate that the surface is wearing thin.\n5. **Leaking**: If you find that your pool is losing more water than usual, it could be due to surface damage. While leaks can have multiple causes, surface issues are often a factor.\n6. **Increased Maintenance**: If you’re spending more time and money on maintaining your pool’s appearance and cleanliness, the surface may be deteriorating.\n7. **Aging**: Most pool finishes last around 10-15 years, depending on the material and maintenance. If your pool is approaching or exceeding this age, it might be time to consider resurfacing.\n8. **Reduced Water Clarity**: Difficulty in maintaining clear water can sometimes be linked to issues with the pool surface, as it might be affecting the filtration system or chemistry.\n\nIf you notice any of these signs, it’s a good idea to consult with Pool Tek Resurfacing in Sydney. We can assess the condition of your pool and recommend whether resurfacing is needed and what type of surface would be best for your situation.\n\nFor pool resurfacing in Sydney, call us on 0481 302 221, [contact us here](https://pooltekresurfacing.com.au/contact-2/), or [email us](mailto:info@pooltekresurfacing.com.au).\n\nSee our [Google Reviews](https://www.google.com/search?q=Pool+Tek+Resurfacing&stick=H4sIAAAAAAAA_-NgU1IxqLA0MDY0MDIzNUhLMTYwSrEyqEgyMk1NNLJMTQZKmBonmi9iFQnIz89RCEnNVghKLS4tSktMzsxLBwBHSvqJPwAAAA&hl=en&mat=CXFiO-66DIhiElcBezTaAVerrjCza5Ka6OGQVmRDh-FapXLQTk6t4ap-Px3oCLM2D3LRsyOIgPMgqPrqo3Ng3L_tBCfXgx26DgTL8TghrDLC1d6NKHIP1b03eKAB2c8FHGgaCAcGFSlSJdn6&authuser=1#lrd=0x903102650fd302d:0xb25ea29ec31053a7,1,,,,).\n\n![When Your Pool Needs Resurfacing](https://pooltekresurfacing.com.au/wp-content/uploads/2024/09/Screenshot-2023-09-07-234009.png)\n\nShare:\n\n[Previous Post](https://pooltekresurfacing.com.au/pool-surface-cracks-in-sydney-causes-and-solutions/)\n\n[Next Post](https://pooltekresurfacing.com.au/pool-renovation-services-in-sydney/)\n\n### Leave a Reply [Cancel reply](https://pooltekresurfacing.com.au/how-to-tell-when-your-pool-needs-resurfacing/\\#respond)\n\nYour email address will not be published. Required fields are marked \\*\n\nPost Comment","metadata":{"og:url":"https://pooltekresurfacing.com.au/how-to-tell-when-your-pool-needs-resurfacing/","twitter:data2":"2 minutes","ogSiteName":"Pool Tek Resurfacing","twitter:card":"summary_large_image","ogImage":"https://pooltekresurfacing.com.au/wp-content/uploads/2024/09/Screenshot-2023-09-07-234009.png","ogTitle":"How To Tell When Your Pool Needs Resurfacing - Pool Tek Resurfacing","og:type":"article","twitter:label2":"Est. reading time","modifiedTime":"2026-03-10T05:20:00+00:00","ogLocale":"en_US","language":"en-US","viewport":"width=device-width, initial-scale=1, shrink-to-fit=no","og:title":"How To Tell When Your Pool Needs Resurfacing - Pool Tek Resurfacing","og:image":"https://pooltekresurfacing.com.au/wp-content/uploads/2024/09/Screenshot-2023-09-07-234009.png","og:image:type":"image/png","title":"How To Tell When Your Pool Needs Resurfacing - Pool Tek Resurfacing","msapplication-TileImage":"https://pooltekresurfacing.com.au/wp-content/uploads/2024/03/service_2_2-1.svg","article:published_time":"2026-03-10T05:19:47+00:00","twitter:label1":"Written by","description":"When Your Pool Needs Resurfacing | Knowing when your pool needs resurfacing is key to maintaining its appearance, functionality, and safety.","og:locale":"en_US","og:description":"When Your Pool Needs Resurfacing | Knowing when your pool needs resurfacing is key to maintaining its appearance, functionality, and safety.","og:image:width":"399","article:modified_time":"2026-03-10T05:20:00+00:00","og:image:height":"297","publishedTime":"2026-03-10T05:19:47+00:00","robots":"index, follow, max-image-preview:large, max-snippet:-1, max-video-preview:-1","og:site_name":"Pool Tek Resurfacing","author":"admin","ogUrl":"https://pooltekresurfacing.com.au/how-to-tell-when-your-pool-needs-resurfacing/","ogDescription":"When Your Pool Needs Resurfacing | Knowing when your pool needs resurfacing is key to maintaining its appearance, functionality, and safety.","twitter:data1":"admin","generator":["WordPress 6.9.4","WooCommerce 9.2.5","Redux 4.5.9","Elementor 3.24.3; features: e_font_icon_svg, additional_custom_breakpoints, e_optimized_control_loading, e_element_cache; settings: css_print_method-external, google_font-enabled, font_display-swap"],"favicon":"https://pooltekresurfacing.com.au/wp-content/uploads/2024/03/service_2_2-1.svg","scrapeId":"019d989f-b379-75aa-adf2-6461e01b4483","sourceURL":"https://pooltekresurfacing.com.au/how-to-tell-when-your-pool-needs-resurfacing/","url":"https://pooltekresurfacing.com.au/how-to-tell-when-your-pool-needs-resurfacing/","statusCode":200,"contentType":"text/html; charset=UTF-8","timezone":"America/New_York","proxyUsed":"basic","cacheState":"miss","indexId":"1a96eee3-f04a-486f-bb29-39ddece5a593","creditsUsed":1}}]}}